unirio/__init__.py
unirio/sie/__init__.py
unirio/sie/base.py
unirio/sie/exceptions.py
unirio/sie/SIEAlunos.py
unirio/sie/SIEBancos.py
unirio/sie/SIEBolsistas.py
unirio/sie/SIECaixaPostal.py
unirio/sie/SIEDocumento.py
unirio/sie/SIEEntidadesExternas.py
unirio/sie/SIEFuncionarios.py
unirio/sie/SIEParametros.py
unirio/sie/SIEPessoas.py
unirio/sie/SIEProcesso.py
unirio/sie/SIEProjetos.py
unirio/sie/SIEProjetosPesquisa.py
unirio/sie/SIEServidores.py
unirio/sie/SIETabEstruturada.py
unirio/sie/utils.py
unirio/sie/adapters/__init__.py
unirio/sie/adapters/base.py
unirio/sie/adapters/web2py.py
unirio_sie-0.0.1.dist-info/DESCRIPTION.rst
unirio_sie-0.0.1.dist-info/METADATA
unirio_sie-0.0.1.dist-info/metadata.json
unirio_sie-0.0.1.dist-info/pbr.json
unirio_sie-0.0.1.dist-info/RECORD
unirio_sie-0.0.1.dist-info/top_level.txt
unirio_sie-0.0.1.dist-info/WHEEL
