Metadata-Version: 2.0
Name: unirio-sie
Version: 0.0.1
Summary: Python DAO module for SIE(Sistema de Informações para o Ensino) academic administration solution.
Home-page: https://github.com/unirio-dtic/unirio-sie
Author: Diogo Magalhães Martins
Author-email: magalhaesmartins@icloud.com
License: GPLv2
Keywords: unirio api sie development
Platform: UNKNOWN
Classifier: Development Status :: 1 - Planning
Classifier: Intended Audience :: Developers
Classifier: Intended Audience :: Education
Classifier: License :: Public Domain
Classifier: Natural Language :: English
Classifier: Operating System :: OS Independent
Classifier: Programming Language :: Python :: 2.7
Classifier: Programming Language :: Python :: 3
Classifier: Programming Language :: Python :: 3.3
Classifier: Programming Language :: Python :: 3.4
Classifier: Programming Language :: Python :: 3.5
Classifier: Topic :: Software Development :: Libraries
Classifier: Topic :: Internet :: WWW/HTTP
Classifier: Topic :: Internet :: WWW/HTTP :: Dynamic Content
Requires-Dist: deprecate
Requires-Dist: unirio-api (>=1.0.0)
